{"about.md":"DAWXuMnR","doc-text_android_android01.md":"BZmahH1C","doc-text_android_android02.md":"BaEKzniX","doc-text_android_android03.md":"Do_EL5XZ","doc-text_android_android04.md":"Ucx-36L2","doc-text_android_android05.md":"BesO4mRq","doc-text_android_android06.md":"DHROcG0e","doc-text_android_android07.md":"DaIrF0Xp","doc-text_android_android08.md":"B2LorJJE","doc-text_android_android09.md":"CYWsyQCE","doc-text_android_android10.md":"qz3jOZBc","doc-text_android_android11.md":"yyFNlB6q","doc-text_android_android12.md":"Bx0Hcz-B","doc-text_android_android13.md":"BoLhEnnP","doc-text_android_android14.md":"CN-n4Fz-","doc-text_android_android15.md":"BEFSzWLd","doc-text_android_android16.md":"BBHzxJUw","doc-text_android_android17.md":"DjeQrrMS","doc-text_bootstrap_bootstrap01.md":"DOQlfsB3","doc-text_bootstrap_bootstrap02.md":"DWcNRcbL","doc-text_bootstrap_bootstrap03.md":"BBpCvgU-","doc-text_compile_练习题答案.md":"BAPo5k1b","doc-text_compile_编译原理01.md":"BALOm7UB","doc-text_compile_编译原理02.md":"CCHhTTB-","doc-text_datastruct_数据结构的三要素.md":"C-PhiXRn","doc-text_datastruct_算法.md":"CW5cMsCr","doc-text_emu_emu01.md":"Bf7pwon5","doc-text_emu_emu02.md":"BURi6HC7","doc-text_emu_emu03.md":"Ci4H06Wn","doc-text_emu_emu04.md":"BUUGgFj2","doc-text_emu_emu05.md":"WZCRSRZN","doc-text_emu_emu06.md":"HI028G_Z","doc-text_emu_emu07.md":"C93BkzV-","doc-text_emu_emu08.md":"byWinEaS","doc-text_emu_emu09.md":"DkrhPns1","doc-text_emu_emu10.md":"BaX3yB_k","doc-text_emu_emu11.md":"CpvxXIqT","doc-text_emu_emu12.md":"D_QWRpaH","doc-text_emu_emu13.md":"DDYqWDss","doc-text_emu_emu14.md":"CKlx77PF","doc-text_emu_emu15.md":"Bx5mG2TA","doc-text_emu_emu16.md":"DL5uGyuV","doc-text_interview_css 属性计算过程.md":"BZXrKmX6","doc-text_interview_事件循环.md":"Gw_wR1BW","doc-text_interview_你不知道的 css 之包含块.md":"CfZUuu4B","doc-text_interview_前端面试题.md":"B7NG0mj7","doc-text_java_javase_cmd的使用和dos命令的使用.md":"D_olqnT_","doc-text_java_javase_gui.md":"CU0xAroC","doc-text_java_javase_io.md":"B7zsH3zp","doc-text_java_javase_jvm入门.md":"BuFQe0EB","doc-text_java_javase_基础.md":"mexomi7D","doc-text_java_javase_多线程.md":"CAdXHBRA","doc-text_java_javase_常用类.md":"Vd3_QBPz","doc-text_java_javase_异常.md":"Bbnz8tDe","doc-text_java_javase_数组.md":"CKnYCE6B","doc-text_java_javase_方法.md":"CiMiOojO","doc-text_java_javase_注解和反射se总结.md":"M-bVb8Uc","doc-text_java_javase_流程控制.md":"BIfECEvf","doc-text_java_javase_网络编程.md":"DXTKR0dV","doc-text_java_javase_集合.md":"DxtHcSlq","doc-text_java_javase_面向对象.md":"88mKooKe","doc-text_java_mybatis_mybatis.md":"Cr0csd_i","doc-text_java_mybatisplus_mybatisplus快速入门.md":"BeQqBkc8","doc-text_java_spring_spring.md":"CgJxnrjS","doc-text_java_springboot_shiro.md":"DV_SG_XB","doc-text_java_springboot_springboot01：hello_world！.md":"JQEmBntQ","doc-text_java_springboot_springboot02：运行原理初探.md":"BSjiI_dU","doc-text_java_springboot_springboot03：yaml配置注入.md":"BMidayPY","doc-text_java_springboot_springboot04：jsr303数据校验及多环境切换.md":"Brm4j-Z-","doc-text_java_springboot_springboot05：自动配置原理.md":"D2jAjzgV","doc-text_java_springboot_springboot06：自定义starter.md":"CEJMih8B","doc-text_java_springboot_springboot07：整合jdbc.md":"Dv2oLFnK","doc-text_java_springboot_springboot08：整合druid.md":"DwmfIaWX","doc-text_java_springboot_springboot09：整合mybatis.md":"Gmh43wvQ","doc-text_java_springboot_springboot10：web开发静态资源处理.md":"DBu4Ntrx","doc-text_java_springboot_springboot11：thymeleaf模板引擎.md":"DtxfzwH4","doc-text_java_springboot_springboot12：mvc自动配置原理.md":"D8gKwCxD","doc-text_java_springboot_springboot13：页面国际化.md":"B7LYefWY","doc-text_java_springboot_springboot14：swagger.md":"C2RBcO15","doc-text_java_springboot_springboot15：异步、定时、邮件任务.md":"DJME9iSV","doc-text_java_springboot_springboot16：富文本编辑器.md":"CRqPjwN0","doc-text_java_springboot_springboot17：dubbo和zookeeper集成.md":"63QnV7Kr","doc-text_java_springboot_springboot18：集成springsecurity.md":"Cg2wgqTc","doc-text_java_springboot_springbootpom包.md":"DVkvPg_4","doc-text_java_springboot_什么是springboot.md":"vJ2LNjf1","doc-text_java_springboot_员工管理.md":"r-RX18Hr","doc-text_java_springboot_说明.md":"BNEzKt_4","doc-text_java_springcloud_springcloud.md":"CrYVa1rf","doc-text_java_springcloudalibaba_chapter01.md":"BOlRWyA9","doc-text_java_springcloudalibaba_chapter02.md":"BDA8gh0F","doc-text_java_springcloudalibaba_chapter03.md":"BmndVIsJ","doc-text_java_springcloudalibaba_chapter04.md":"BfgTln6M","doc-text_java_springcloudalibaba_chapter05.md":"DOHuqzVr","doc-text_java_springcloudnetflix_springcloud.md":"BsCdtSVI","doc-text_java_springmvc_springmvc.md":"sk7O3WCe","doc-text_linux_chapter01介绍.md":"BgNe0TFr","doc-text_linux_chapter02.md":"Bgi2BnYa","doc-text_linux_linux快速入门.md":"Cajdexro","doc-text_python_开始学习python.md":"CU5bKzRk","doc-text_python_数据类型和运算符.md":"kjjtX10m","doc-text_python_顺序、选择、循环.md":"BuVSqraI","doc-text_redis_redis.md":"BYoYsXp5","doc-text_uniapp_uniapp01.md":"G5CqPFZo","doc-text_uniapp_uniapp02.md":"DvINJPOY","doc-text_uniapp_uniapp03.md":"D7YcjcB8","doc-text_vitepress_vitepress01.md":"CxzUNNlM","doc-text_vitepress_vitepress02.md":"DghKe3aQ","doc-text_vitepress_vitepress03.md":"Dh76cIT8","doc-text_vitepress_vitepress04.md":"B48CFtcT","doc-text_vitepress_vitepress05.md":"BkKKwOmG","doc-text_vitepress_vitepress06.md":"DcyP9LPe","doc-text_vitepress_vitepress07.md":"D8Jdy8SQ","doc-text_vitepress_vitepress08.md":"BsGRUwLO","doc-text_vitepress_vitepress09.md":"B8NsVBg5","doc-text_vue_vue201.md":"C2Sr2cHj","doc-text_vue_vue202.md":"CiqmAbFS","doc-text_vue_vue203.md":"D9_KQSD9","doc-text_vue_vue204.md":"Ccl4g429","doc-text_vue_vue205.md":"Ck10yflA","doc-text_vue_vue206.md":"DdigubpC","doc-text_vue_vue207.md":"Dl4Jorun","doc-text_vue_vue208.md":"Cu4HBF4N","doc-text_wx_wx01.md":"Be9elAcw","doc-text_wx_wx02.md":"BiEBbnN4","doc-text_wx_wx03.md":"DZqTazdK","doc-text_wx_wx04.md":"CPx109Ok","doc-text_wx_wx05.md":"DO2ctHHK","doc-text_wx_wx06.md":"C0-kS5vM","doc-text_wx_wx07.md":"Abc4Jkdv","doc-text_wx_wx08.md":"Ca41jEDO","doc-text_wx_wx09.md":"BD4oOPG2","doc-text_wx_wx10.md":"B6e4W0Xa","doc-text_wx_wx11.md":"CXWn2huW","doc-text_wx_wx12.md":"BHHkMhME","doc-text_wx_wx13.md":"BsLqfYzo","doc-text_wx_wx14.md":"DkEGDPTF","doc-text_wx_wx15.md":"DyUxiiOz","doc-text_wx_wx16.md":"CwQIxJm7","doc-text_wx_wx17.md":"CdiBidKl","doc-text_wx_wx18.md":"Dl-EA3j3","doc-text_wx_wx19.md":"Co7Z-n-I","doc-text_wx_wx20.md":"BMnKqAe1","doc-text_wx_wx21.md":"QAkmGFIA","doc-text_wx_wx22.md":"hocrhahK","doc-text_wx_wx23.md":"YMqVb4lc","doc-text_wx_wx24.md":"DJwfgo62","doc-text_wx_wx25.md":"CZzsM_p5","doc-text_wx_wx26.md":"yYIvxJIQ","doc-text_wx_wx27.md":"BqeMS0ZD","doc-text_wx_wx28.md":"BKE1tQWp","doc-text_一键生成mapper和实体类_generator.md":"z95CLJCW","index.md":"C_AIPZPe","readme.md":"DsM0kZfV"}
